{"schema":{"vm":{"type":{"dataType":"reference","isMultiple":false,"referenceType":"VC:VirtualMachine"},"label":"Virtual machine on which to mount a CD-ROM\n","id":"vm","constraints":{"required":true}},"GENERATED_6aa4383c-c516-4a1f-953d-d1bc03efd4bb":{"type":{"dataType":"string","isMultiple":false},"id":"GENERATED_6aa4383c-c516-4a1f-953d-d1bc03efd4bb","constraints":{},"default":"'connectAtPowerOn' field is ignored when selecting  \"Client Device\" device type.\n\n'filePath' field is only taken into account when selecting \"Datastore ISO File\" device type.\n"},"filePath":{"type":{"dataType":"string","isMultiple":false},"label":"ISO file path in datastore file format, for example [MY_DATASTORE] data/image.iso\n","id":"filePath","constraints":{}}},"layout":{"pages":[{"id":"page_1","title":"VM","sections":[{"id":"section_0","fields":[{"id":"vm","display":"valuePicker"}]}]},{"id":"page_2","title":"CD-ROM","sections":[{"id":"section_1","fields":[{"id":"GENERATED_6aa4383c-c516-4a1f-953d-d1bc03efd4bb","display":"text"}]},{"id":"section_4","fields":[{"id":"filePath","display":"textField"}]}]}]},"itemId":""}